[
    {
        "name": "CapricanDRJ: Hades' Star Community Data",
        "redirectUrl": "https://ws.tsl.rocks/",
        "iconUrl": "https://cdn.discordapp.com/avatars/454459089720967168/a_473b9e16d64a9a03f1d6449bed118e3f.gif?size=4096"
    },
    {
        "name": "WS Community Leaderboard",
        "redirectUrl": "https://tsl.rocks/",
        "iconUrl": "https://cdn.discordapp.com/icons/800598168906760202/bf522862eab686114b70b618561b50e1.webp?size=640"
    },
    {
        "name": "C3",
        "redirectUrl": "https://ws.tsl.rocks/",
        "iconUrl": "https://example.com/icon.jpg"
    },
    {
        "name": "Another Person4",
        "redirectUrl": "https://discord.com/users/987654321",
        "iconUrl": "https://example.com/icon2.jpg"
    }
]
